Metadata-Version: 2.1
Name: dorkylever-lama-phenotype-detection
Version: 1.0.1
Summary: Phenotype detection pipeline for finding abnormalities in mouse embryos
Home-page: https://github.com/mpi2/LAMA
Download-URL: https://github.com/dorkylever/LAMA/archive/refs/tags/1.0.1.tar.gz
Author: Neil Horner
Author-email: n.horner@har.mrc.ac.uk, bit@har.mrc.ac.uk
License: Apache2
Keywords: image processing,bioinformatics,phenotype
Classifier: Programming Language :: Python :: 3
Classifier: License :: OSI Approved :: MIT License
Classifier: Operating System :: OS Independent
License-File: LICENCE.md
Requires-Dist: appdirs
Requires-Dist: setuptools (==59.8.0)
Requires-Dist: matplotlib (>=2.2.0)
Requires-Dist: numpy (>=1.20)
Requires-Dist: pandas (>=1.1.0)
Requires-Dist: scikit-learn (>=1.0.2)
Requires-Dist: scipy (>=1.1.0)
Requires-Dist: scikit-image (==0.17.2)
Requires-Dist: seaborn (>=0.9.0)
Requires-Dist: statsmodels (>=0.9.0)
Requires-Dist: PyYAML (>=3.13)
Requires-Dist: SimpleITK (>=2.1.0)
Requires-Dist: pyradiomics (>=3.0.1)
Requires-Dist: threadpoolctl (==3.1.0)
Requires-Dist: imbalanced-learn (==0.9.0)
Requires-Dist: raster-geometry
Requires-Dist: filelock
Requires-Dist: psutil
Requires-Dist: plotly
Requires-Dist: logzero
Requires-Dist: addict
Requires-Dist: toml
Requires-Dist: pynrrd
Requires-Dist: pytest
Requires-Dist: mlxtend
Requires-Dist: tqdm
Requires-Dist: gitpython
Requires-Dist: pacmap
Requires-Dist: shap
Requires-Dist: joblib
Requires-Dist: wheel
Provides-Extra: dev
Requires-Dist: h5py ; extra == 'dev'
